odoo/addons/crm_deduplicate_acl/README.rst
odoo/addons/crm_deduplicate_acl/__init__.py
odoo/addons/crm_deduplicate_acl/__manifest__.py
odoo/addons/crm_deduplicate_acl/i18n/de.po
odoo/addons/crm_deduplicate_acl/i18n/es.po
odoo/addons/crm_deduplicate_acl/i18n/hr.po
odoo/addons/crm_deduplicate_acl/i18n/it.po
odoo/addons/crm_deduplicate_acl/i18n/nl_NL.po
odoo/addons/crm_deduplicate_acl/i18n/pt_BR.po
odoo/addons/crm_deduplicate_acl/i18n/sk.po
odoo/addons/crm_deduplicate_acl/i18n/sl.po
odoo/addons/crm_deduplicate_acl/i18n/tr.po
odoo/addons/crm_deduplicate_acl/i18n/zh_CN.po
odoo/addons/crm_deduplicate_acl/images/perms.png
odoo/addons/crm_deduplicate_acl/models/__init__.py
odoo/addons/crm_deduplicate_acl/models/res_partner.py
odoo/addons/crm_deduplicate_acl/security/crm_deduplicate_acl_security.xml
odoo/addons/crm_deduplicate_acl/static/description/icon.png
odoo/addons/crm_deduplicate_acl/static/description/icon.svg
odoo/addons/crm_deduplicate_acl/tests/__init__.py
odoo/addons/crm_deduplicate_acl/tests/test_crm_deduplicate_acl.py
odoo/addons/crm_deduplicate_acl/views/base_partner_merge_view.xml
odoo/addons/crm_deduplicate_acl/wizards/__init__.py
odoo/addons/crm_deduplicate_acl/wizards/partner_merge.py
odoo/addons/crm_deduplicate_acl/wizards/partner_merge_view.xml
odoo11_addon_crm_deduplicate_acl-11.0.1.0.0.dist-info/DESCRIPTION.rst
odoo11_addon_crm_deduplicate_acl-11.0.1.0.0.dist-info/METADATA
odoo11_addon_crm_deduplicate_acl-11.0.1.0.0.dist-info/RECORD
odoo11_addon_crm_deduplicate_acl-11.0.1.0.0.dist-info/WHEEL
odoo11_addon_crm_deduplicate_acl-11.0.1.0.0.dist-info/metadata.json
odoo11_addon_crm_deduplicate_acl-11.0.1.0.0.dist-info/top_level.txt
